Mockdown-0.1.0.dev5.dist-info/DESCRIPTION.rst
Mockdown-0.1.0.dev5.dist-info/METADATA
Mockdown-0.1.0.dev5.dist-info/RECORD
Mockdown-0.1.0.dev5.dist-info/WHEEL
Mockdown-0.1.0.dev5.dist-info/entry_points.txt
Mockdown-0.1.0.dev5.dist-info/metadata.json
Mockdown-0.1.0.dev5.dist-info/top_level.txt
mockdown/__init__.py
mockdown/__init__.pyc
mockdown/app.py
mockdown/mockdown.py
mockdown/mockdown.pyc
mockdown/templates/index.html
