Metadata-Version: 2.0
Name: Mockdown
Version: 0.1.0.dev5
Summary: HTML mockups simplified!
Home-page: https://github.com/anandology/mockdown
Author: Anand Chitipothu
Author-email: anandology@gmail.com
License: BSD
Keywords: mockdown
Platform: UNKNOWN
Classifier: Development Status :: 2 - Pre-Alpha
Classifier: Intended Audience :: Developers
Classifier: License :: OSI Approved :: BSD License
Classifier: Natural Language :: English
Classifier: Programming Language :: Python :: 2
Classifier: Programming Language :: Python :: 2.7
Classifier: Programming Language :: Python :: 3
Classifier: Programming Language :: Python :: 3.3
Classifier: Programming Language :: Python :: 3.4
Classifier: Programming Language :: Python :: 3.5
Classifier: Programming Language :: Python :: 3.6
Requires-Dist: Faker (>=0.7.7)
Requires-Dist: Flask (>=0.10)
Requires-Dist: Jinja2 (>=2.4)
Requires-Dist: PyYAML (>=3.11)
Requires-Dist: pathlib (==1.0.1)
